aiogram_utcpicker/__init__.py
aiogram_utcpicker/utcpicker.py
aiogram_utcpicker-0.1.2.dist-info/LICENSE
aiogram_utcpicker-0.1.2.dist-info/METADATA
aiogram_utcpicker-0.1.2.dist-info/WHEEL
aiogram_utcpicker-0.1.2.dist-info/RECORD
