Metadata-Version: 2.1
Name: aiogram-utcpicker
Version: 0.1.2
Summary: An inline tool for selecting valid timezone differences to UTC
License: MIT
Author: alexanderchainsaw
Author-email: alexanderkolesov.contact@gmail.com
Requires-Python: >=3.11,<4.0
Classifier: License :: OSI Approved :: MIT License
Classifier: Programming Language :: Python :: 3
Classifier: Programming Language :: Python :: 3.11
Classifier: Programming Language :: Python :: 3.12
Classifier: Programming Language :: Python :: 3.13
Requires-Dist: aiogram (==3.13.1)
Requires-Dist: pytest (>=8.3.3,<9.0.0)
Requires-Dist: pytest-asyncio (>=0.24.0,<0.25.0)
